{
  "directed": false,
  "multigraph": false,
  "graph": {
    "hyperedges": [
      {
        "id": "static_self_contained_github_pages_model",
        "label": "Static Self-Contained GitHub Pages Model",
        "nodes": [
          "agents_static_github_pages_site",
          "agents_standalone_html_pages",
          "agents_no_build_system_or_shared_runtime",
          "readme_static_github_pages_cookbook",
          "readme_self_contained_html_pages",
          "readme_no_build_step_required",
          "index_standalone_html_page",
          "index_inline_page_specific_css"
        ],
        "relation": "form",
        "confidence": "INFERRED",
        "confidence_score": 0.95,
        "source_file": "AGENTS.md"
      },
      {
        "id": "devsecops_cookbook_topic_scope",
        "label": "DevSecOps Cookbook Topic Scope",
        "nodes": [
          "agents_devsecops_topic_scope",
          "readme_devsecops_topic_scope",
          "index_cookbook_topics",
          "index_cli_usage",
          "index_security_scanning",
          "index_ci_cd",
          "index_kubernetes",
          "index_cloud_identity"
        ],
        "relation": "form",
        "confidence": "INFERRED",
        "confidence_score": 0.85,
        "source_file": "index.html"
      },
      {
        "id": "recipe_documentation_pattern",
        "label": "Recipe Documentation Pattern",
        "nodes": [
          "agents_devsecops_recipe_page_structure",
          "agents_copy_pasteable_commands",
          "agents_safety_notes",
          "index_tool_recipes",
          "index_workflow_playbooks",
          "index_command_patterns"
        ],
        "relation": "form",
        "confidence": "INFERRED",
        "confidence_score": 0.85,
        "source_file": "AGENTS.md"
      }
    ]
  },
  "nodes": [
    {
      "label": "AGENTS.md",
      "file_type": "document",
      "source_file": "AGENTS.md",
      "source_location": "L1",
      "id": "agents",
      "community": 1,
      "norm_label": "agents.md"
    },
    {
      "label": "Project Instructions",
      "file_type": "document",
      "source_file": "AGENTS.md",
      "source_location": "L1",
      "id": "agents_project_instructions",
      "community": 1,
      "norm_label": "project instructions"
    },
    {
      "label": "Site Shape",
      "file_type": "document",
      "source_file": "AGENTS.md",
      "source_location": "L5",
      "id": "agents_site_shape",
      "community": 1,
      "norm_label": "site shape"
    },
    {
      "label": "Content Conventions",
      "file_type": "document",
      "source_file": "AGENTS.md",
      "source_location": "L13",
      "id": "agents_content_conventions",
      "community": 1,
      "norm_label": "content conventions"
    },
    {
      "label": "Quality Bar",
      "file_type": "document",
      "source_file": "AGENTS.md",
      "source_location": "L23",
      "id": "agents_quality_bar",
      "community": 1,
      "norm_label": "quality bar"
    },
    {
      "label": "README.md",
      "file_type": "document",
      "source_file": "README.md",
      "source_location": "L1",
      "id": "readme",
      "community": 5,
      "norm_label": "readme.md"
    },
    {
      "label": "DevSecOps Cookbook Knowledge",
      "file_type": "document",
      "source_file": "README.md",
      "source_location": "L1",
      "id": "readme_devsecops_cookbook_knowledge",
      "community": 5,
      "norm_label": "devsecops cookbook knowledge"
    },
    {
      "label": "Structure",
      "file_type": "document",
      "source_file": "README.md",
      "source_location": "L6",
      "id": "readme_structure",
      "community": 5,
      "norm_label": "structure"
    },
    {
      "label": "Publishing",
      "file_type": "document",
      "source_file": "README.md",
      "source_location": "L13",
      "id": "readme_publishing",
      "community": 5,
      "norm_label": "publishing"
    }
  ],
  "links": [
    {
      "relation": "contains",
      "confidence": "EXTRACTED",
      "source_file": "AGENTS.md",
      "source_location": "L1",
      "weight": 1.0,
      "source": "agents",
      "target": "agents_project_instructions",
      "confidence_score": 1.0
    },
    {
      "relation": "contains",
      "confidence": "EXTRACTED",
      "source_file": "AGENTS.md",
      "source_location": "L13",
      "weight": 1.0,
      "source": "agents_project_instructions",
      "target": "agents_content_conventions",
      "confidence_score": 1.0
    },
    {
      "relation": "contains",
      "confidence": "EXTRACTED",
      "source_file": "AGENTS.md",
      "source_location": "L23",
      "weight": 1.0,
      "source": "agents_project_instructions",
      "target": "agents_quality_bar",
      "confidence_score": 1.0
    },
    {
      "relation": "contains",
      "confidence": "EXTRACTED",
      "source_file": "AGENTS.md",
      "source_location": "L5",
      "weight": 1.0,
      "source": "agents_project_instructions",
      "target": "agents_site_shape",
      "confidence_score": 1.0
    },
    {
      "relation": "contains",
      "confidence": "EXTRACTED",
      "source_file": "README.md",
      "source_location": "L1",
      "weight": 1.0,
      "source": "readme",
      "target": "readme_devsecops_cookbook_knowledge",
      "confidence_score": 1.0
    },
    {
      "relation": "contains",
      "confidence": "EXTRACTED",
      "source_file": "README.md",
      "source_location": "L13",
      "weight": 1.0,
      "source": "readme_devsecops_cookbook_knowledge",
      "target": "readme_publishing",
      "confidence_score": 1.0
    },
    {
      "relation": "contains",
      "confidence": "EXTRACTED",
      "source_file": "README.md",
      "source_location": "L6",
      "weight": 1.0,
      "source": "readme_devsecops_cookbook_knowledge",
      "target": "readme_structure",
      "confidence_score": 1.0
    }
  ],
  "hyperedges": [
    {
      "id": "static_self_contained_github_pages_model",
      "label": "Static Self-Contained GitHub Pages Model",
      "nodes": [
        "agents_static_github_pages_site",
        "agents_standalone_html_pages",
        "agents_no_build_system_or_shared_runtime",
        "readme_static_github_pages_cookbook",
        "readme_self_contained_html_pages",
        "readme_no_build_step_required",
        "index_standalone_html_page",
        "index_inline_page_specific_css"
      ],
      "relation": "form",
      "confidence": "INFERRED",
      "confidence_score": 0.95,
      "source_file": "AGENTS.md"
    },
    {
      "id": "devsecops_cookbook_topic_scope",
      "label": "DevSecOps Cookbook Topic Scope",
      "nodes": [
        "agents_devsecops_topic_scope",
        "readme_devsecops_topic_scope",
        "index_cookbook_topics",
        "index_cli_usage",
        "index_security_scanning",
        "index_ci_cd",
        "index_kubernetes",
        "index_cloud_identity"
      ],
      "relation": "form",
      "confidence": "INFERRED",
      "confidence_score": 0.85,
      "source_file": "index.html"
    },
    {
      "id": "recipe_documentation_pattern",
      "label": "Recipe Documentation Pattern",
      "nodes": [
        "agents_devsecops_recipe_page_structure",
        "agents_copy_pasteable_commands",
        "agents_safety_notes",
        "index_tool_recipes",
        "index_workflow_playbooks",
        "index_command_patterns"
      ],
      "relation": "form",
      "confidence": "INFERRED",
      "confidence_score": 0.85,
      "source_file": "AGENTS.md"
    }
  ],
  "built_at_commit": "ef5c3810e58080fb0f2288dc654988e7d8e23ddf"
}